setup.py
cxeeprom_tool/__init__.py
cxeeprom_tool/process_types.py
cxeeprom_tool/write_image.py
cxeeprom_tool.egg-info/PKG-INFO
cxeeprom_tool.egg-info/SOURCES.txt
cxeeprom_tool.egg-info/dependency_links.txt
cxeeprom_tool.egg-info/requires.txt
cxeeprom_tool.egg-info/top_level.txt
cxeeprom_tool/defs/__init__.py
cxeeprom_tool/defs/types.py
cxeeprom_tool/defs/variables.py
scripts/cxeeprom_tool