Metadata-Version: 1.1
Name: cxeeprom-tool
Version: 3.0
Summary: Calxeda Configuration EEPROM image tool
Home-page: UNKNOWN
Author: UNKNOWN
Author-email: UNKNOWN
License: UNKNOWN
Platform: UNKNOWN
Classifier: License :: OSI Approved :: BSD License
Classifier: Programming Language :: Python :: 2.7
